devopsjourney/__init__.py
devopsjourney/channel.py
devopsjourney-0.0.4.dist-info/LICENSE
devopsjourney-0.0.4.dist-info/METADATA
devopsjourney-0.0.4.dist-info/WHEEL
devopsjourney-0.0.4.dist-info/top_level.txt
devopsjourney-0.0.4.dist-info/RECORD
